{
  "task": "iterated_nonlinear_map",
  "pattern": [
    "unified-learned-free",
    "unified-learned-free",
    "unified-learned-free",
    "unified-learned-free"
  ],
  "dim": 384,
  "depth": 4,
  "seq_len": 128,
  "batch_size": 32,
  "lr": 0.0003,
  "seed": 123,
  "params": 7874688,
  "disable_autocast": true,
  "use_triton_e88": false,
  "linear_state": null,
  "state_activation": null,
  "use_gate": null,
  "decay_mode": null,
  "gdn_allow_neg_eigval": null,
  "e88_pos_eigval_clamp": null,
  "e88_raw_write": null,
  "knob_lr_mult": 1.0,
  "spec_reg": "coverage",
  "spec_reg_weight": 1.0,
  "spec_reg_anneal": 0.5,
  "curriculum": null,
  "random_baseline_acc": 0.1,
  "steps": [
    {
      "step": 0,
      "train_loss": 260.77801513671875,
      "eval_acc": 0.02520751953125,
      "eval_loss": 123.51372146606445,
      "elapsed_s": 4.289679050445557
    },
    {
      "step": 250,
      "train_loss": 1.7879977226257324,
      "eval_acc": 0.41015625,
      "eval_loss": 1.3137670159339905,
      "elapsed_s": 9.947958707809448
    },
    {
      "step": 500,
      "train_loss": 1.5898394584655762,
      "eval_acc": 0.417236328125,
      "eval_loss": 1.2326436340808868,
      "elapsed_s": 15.562535285949707
    },
    {
      "step": 750,
      "train_loss": 1.5083516836166382,
      "eval_acc": 0.459716796875,
      "eval_loss": 1.1422695815563202,
      "elapsed_s": 21.21497893333435
    },
    {
      "step": 1000,
      "train_loss": 1.5052406787872314,
      "eval_acc": 0.48016357421875,
      "eval_loss": 1.1027126014232635,
      "elapsed_s": 26.880890130996704
    },
    {
      "step": 1250,
      "train_loss": 1.4856455326080322,
      "eval_acc": 0.5120849609375,
      "eval_loss": 1.0595265626907349,
      "elapsed_s": 32.52341079711914
    },
    {
      "step": 1500,
      "train_loss": 1.4800175428390503,
      "eval_acc": 0.5196533203125,
      "eval_loss": 1.0373910069465637,
      "elapsed_s": 38.13399624824524
    },
    {
      "step": 1750,
      "train_loss": 1.4909336566925049,
      "eval_acc": 0.54766845703125,
      "eval_loss": 0.978378415107727,
      "elapsed_s": 43.754162073135376
    },
    {
      "step": 2000,
      "train_loss": 1.5252941846847534,
      "eval_acc": 0.5572509765625,
      "eval_loss": 0.9439973682165146,
      "elapsed_s": 49.38194537162781
    },
    {
      "step": 2250,
      "train_loss": 1.515542984008789,
      "eval_acc": 0.5703125,
      "eval_loss": 0.9031473249197006,
      "elapsed_s": 54.99883222579956
    },
    {
      "step": 2500,
      "train_loss": 1.5969312191009521,
      "eval_acc": 0.58148193359375,
      "eval_loss": 0.884797677397728,
      "elapsed_s": 60.62613821029663
    },
    {
      "step": 2750,
      "train_loss": 1.5353529453277588,
      "eval_acc": 0.58892822265625,
      "eval_loss": 0.8615716993808746,
      "elapsed_s": 66.25797152519226
    },
    {
      "step": 3000,
      "train_loss": 1.54166579246521,
      "eval_acc": 0.60394287109375,
      "eval_loss": 0.8324122726917267,
      "elapsed_s": 71.89495396614075
    },
    {
      "step": 3250,
      "train_loss": 1.4713590145111084,
      "eval_acc": 0.60504150390625,
      "eval_loss": 0.8176198303699493,
      "elapsed_s": 77.52457427978516
    },
    {
      "step": 3500,
      "train_loss": 1.4557788372039795,
      "eval_acc": 0.60845947265625,
      "eval_loss": 0.8026550710201263,
      "elapsed_s": 83.16323351860046
    },
    {
      "step": 3750,
      "train_loss": 1.3694579601287842,
      "eval_acc": 0.63177490234375,
      "eval_loss": 0.7747515141963959,
      "elapsed_s": 88.80745220184326
    },
    {
      "step": 4000,
      "train_loss": 1.3718417882919312,
      "eval_acc": 0.63323974609375,
      "eval_loss": 0.7695555090904236,
      "elapsed_s": 94.46587610244751
    },
    {
      "step": 4250,
      "train_loss": 1.3542674779891968,
      "eval_acc": 0.6529541015625,
      "eval_loss": 0.730123445391655,
      "elapsed_s": 100.1188097000122
    },
    {
      "step": 4500,
      "train_loss": 1.3485074043273926,
      "eval_acc": 0.65386962890625,
      "eval_loss": 0.7238067835569382,
      "elapsed_s": 105.77772331237793
    },
    {
      "step": 4750,
      "train_loss": 1.2687439918518066,
      "eval_acc": 0.65899658203125,
      "eval_loss": 0.719187781214714,
      "elapsed_s": 111.44361710548401
    },
    {
      "step": 4999,
      "train_loss": 1.19524347782135,
      "eval_acc": 0.6624755859375,
      "eval_loss": 0.7050865739583969,
      "elapsed_s": 117.07573103904724
    }
  ],
  "unified_knobs_init": [
    {
      "layer": 0,
      "lambda": [
        0.949999988079071,
        0.949999988079071,
        0.949999988079071,
        0.949999988079071,
        0.949999988079071,
        0.949999988079071,
        0.949999988079071,
        0.949999988079071,
        0.949999988079071,
        0.949999988079071,
        0.949999988079071,
        0.949999988079071,
        0.949999988079071,
        0.949999988079071,
        0.949999988079071,
        0.949999988079071,
        0.949999988079071,
        0.949999988079071,
        0.949999988079071,
        0.949999988079071,
        0.949999988079071,
        0.949999988079071,
        0.949999988079071,
        0.949999988079071,
        0.949999988079071,
        0.949999988079071,
        0.949999988079071,
        0.949999988079071,
        0.949999988079071,
        0.949999988079071,
        0.949999988079071,
        0.949999988079071
      ],
      "beta": [
        0.5,
        0.5,
        0.5,
        0.5,
        0.5,
        0.5,
        0.5,
        0.5,
        0.5,
        0.5,
        0.5,
        0.5,
        0.5,
        0.5,
        0.5,
        0.5,
        0.5,
        0.5,
        0.5,
        0.5,
        0.5,
        0.5,
        0.5,
        0.5,
        0.5,
        0.5,
        0.5,
        0.5,
        0.5,
        0.5,
        0.5,
        0.5
      ],
      "igain": [
        1.0,
        1.0,
        1.0,
        1.0,
        1.0,
        1.0,
        1.0,
        1.0,
        1.0,
        1.0,
        1.0,
        1.0,
        1.0,
        1.0,
        1.0,
        1.0,
        1.0,
        1.0,
        1.0,
        1.0,
        1.0,
        1.0,
        1.0,
        1.0,
        1.0,
        1.0,
        1.0,
        1.0,
        1.0,
        1.0,
        1.0,
        1.0
      ],
      "gamma": [
        0.5,
        0.5,
        0.5,
        0.5,
        0.5,
        0.5,
        0.5,
        0.5,
        0.5,
        0.5,
        0.5,
        0.5,
        0.5,
        0.5,
        0.5,
        0.5,
        0.5,
        0.5,
        0.5,
        0.5,
        0.5,
        0.5,
        0.5,
        0.5,
        0.5,
        0.5,
        0.5,
        0.5,
        0.5,
        0.5,
        0.5,
        0.5
      ],
      "eig_along": [
        0.44999998807907104,
        0.44999998807907104,
        0.44999998807907104,
        0.44999998807907104,
        0.44999998807907104,
        0.44999998807907104,
        0.44999998807907104,
        0.44999998807907104,
        0.44999998807907104,
        0.44999998807907104,
        0.44999998807907104,
        0.44999998807907104,
        0.44999998807907104,
        0.44999998807907104,
        0.44999998807907104,
        0.44999998807907104,
        0.44999998807907104,
        0.44999998807907104,
        0.44999998807907104,
        0.44999998807907104,
        0.44999998807907104,
        0.44999998807907104,
        0.44999998807907104,
        0.44999998807907104,
        0.44999998807907104,
        0.44999998807907104,
        0.44999998807907104,
        0.44999998807907104,
        0.44999998807907104,
        0.44999998807907104,
        0.44999998807907104,
        0.44999998807907104
      ]
    },
    {
      "layer": 1,
      "lambda": [
        0.949999988079071,
        0.949999988079071,
        0.949999988079071,
        0.949999988079071,
        0.949999988079071,
        0.949999988079071,
        0.949999988079071,
        0.949999988079071,
        0.949999988079071,
        0.949999988079071,
        0.949999988079071,
        0.949999988079071,
        0.949999988079071,
        0.949999988079071,
        0.949999988079071,
        0.949999988079071,
        0.949999988079071,
        0.949999988079071,
        0.949999988079071,
        0.949999988079071,
        0.949999988079071,
        0.949999988079071,
        0.949999988079071,
        0.949999988079071,
        0.949999988079071,
        0.949999988079071,
        0.949999988079071,
        0.949999988079071,
        0.949999988079071,
        0.949999988079071,
        0.949999988079071,
        0.949999988079071
      ],
      "beta": [
        0.5,
        0.5,
        0.5,
        0.5,
        0.5,
        0.5,
        0.5,
        0.5,
        0.5,
        0.5,
        0.5,
        0.5,
        0.5,
        0.5,
        0.5,
        0.5,
        0.5,
        0.5,
        0.5,
        0.5,
        0.5,
        0.5,
        0.5,
        0.5,
        0.5,
        0.5,
        0.5,
        0.5,
        0.5,
        0.5,
        0.5,
        0.5
      ],
      "igain": [
        1.0,
        1.0,
        1.0,
        1.0,
        1.0,
        1.0,
        1.0,
        1.0,
        1.0,
        1.0,
        1.0,
        1.0,
        1.0,
        1.0,
        1.0,
        1.0,
        1.0,
        1.0,
        1.0,
        1.0,
        1.0,
        1.0,
        1.0,
        1.0,
        1.0,
        1.0,
        1.0,
        1.0,
        1.0,
        1.0,
        1.0,
        1.0
      ],
      "gamma": [
        0.5,
        0.5,
        0.5,
        0.5,
        0.5,
        0.5,
        0.5,
        0.5,
        0.5,
        0.5,
        0.5,
        0.5,
        0.5,
        0.5,
        0.5,
        0.5,
        0.5,
        0.5,
        0.5,
        0.5,
        0.5,
        0.5,
        0.5,
        0.5,
        0.5,
        0.5,
        0.5,
        0.5,
        0.5,
        0.5,
        0.5,
        0.5
      ],
      "eig_along": [
        0.44999998807907104,
        0.44999998807907104,
        0.44999998807907104,
        0.44999998807907104,
        0.44999998807907104,
        0.44999998807907104,
        0.44999998807907104,
        0.44999998807907104,
        0.44999998807907104,
        0.44999998807907104,
        0.44999998807907104,
        0.44999998807907104,
        0.44999998807907104,
        0.44999998807907104,
        0.44999998807907104,
        0.44999998807907104,
        0.44999998807907104,
        0.44999998807907104,
        0.44999998807907104,
        0.44999998807907104,
        0.44999998807907104,
        0.44999998807907104,
        0.44999998807907104,
        0.44999998807907104,
        0.44999998807907104,
        0.44999998807907104,
        0.44999998807907104,
        0.44999998807907104,
        0.44999998807907104,
        0.44999998807907104,
        0.44999998807907104,
        0.44999998807907104
      ]
    },
    {
      "layer": 2,
      "lambda": [
        0.949999988079071,
        0.949999988079071,
        0.949999988079071,
        0.949999988079071,
        0.949999988079071,
        0.949999988079071,
        0.949999988079071,
        0.949999988079071,
        0.949999988079071,
        0.949999988079071,
        0.949999988079071,
        0.949999988079071,
        0.949999988079071,
        0.949999988079071,
        0.949999988079071,
        0.949999988079071,
        0.949999988079071,
        0.949999988079071,
        0.949999988079071,
        0.949999988079071,
        0.949999988079071,
        0.949999988079071,
        0.949999988079071,
        0.949999988079071,
        0.949999988079071,
        0.949999988079071,
        0.949999988079071,
        0.949999988079071,
        0.949999988079071,
        0.949999988079071,
        0.949999988079071,
        0.949999988079071
      ],
      "beta": [
        0.5,
        0.5,
        0.5,
        0.5,
        0.5,
        0.5,
        0.5,
        0.5,
        0.5,
        0.5,
        0.5,
        0.5,
        0.5,
        0.5,
        0.5,
        0.5,
        0.5,
        0.5,
        0.5,
        0.5,
        0.5,
        0.5,
        0.5,
        0.5,
        0.5,
        0.5,
        0.5,
        0.5,
        0.5,
        0.5,
        0.5,
        0.5
      ],
      "igain": [
        1.0,
        1.0,
        1.0,
        1.0,
        1.0,
        1.0,
        1.0,
        1.0,
        1.0,
        1.0,
        1.0,
        1.0,
        1.0,
        1.0,
        1.0,
        1.0,
        1.0,
        1.0,
        1.0,
        1.0,
        1.0,
        1.0,
        1.0,
        1.0,
        1.0,
        1.0,
        1.0,
        1.0,
        1.0,
        1.0,
        1.0,
        1.0
      ],
      "gamma": [
        0.5,
        0.5,
        0.5,
        0.5,
        0.5,
        0.5,
        0.5,
        0.5,
        0.5,
        0.5,
        0.5,
        0.5,
        0.5,
        0.5,
        0.5,
        0.5,
        0.5,
        0.5,
        0.5,
        0.5,
        0.5,
        0.5,
        0.5,
        0.5,
        0.5,
        0.5,
        0.5,
        0.5,
        0.5,
        0.5,
        0.5,
        0.5
      ],
      "eig_along": [
        0.44999998807907104,
        0.44999998807907104,
        0.44999998807907104,
        0.44999998807907104,
        0.44999998807907104,
        0.44999998807907104,
        0.44999998807907104,
        0.44999998807907104,
        0.44999998807907104,
        0.44999998807907104,
        0.44999998807907104,
        0.44999998807907104,
        0.44999998807907104,
        0.44999998807907104,
        0.44999998807907104,
        0.44999998807907104,
        0.44999998807907104,
        0.44999998807907104,
        0.44999998807907104,
        0.44999998807907104,
        0.44999998807907104,
        0.44999998807907104,
        0.44999998807907104,
        0.44999998807907104,
        0.44999998807907104,
        0.44999998807907104,
        0.44999998807907104,
        0.44999998807907104,
        0.44999998807907104,
        0.44999998807907104,
        0.44999998807907104,
        0.44999998807907104
      ]
    },
    {
      "layer": 3,
      "lambda": [
        0.949999988079071,
        0.949999988079071,
        0.949999988079071,
        0.949999988079071,
        0.949999988079071,
        0.949999988079071,
        0.949999988079071,
        0.949999988079071,
        0.949999988079071,
        0.949999988079071,
        0.949999988079071,
        0.949999988079071,
        0.949999988079071,
        0.949999988079071,
        0.949999988079071,
        0.949999988079071,
        0.949999988079071,
        0.949999988079071,
        0.949999988079071,
        0.949999988079071,
        0.949999988079071,
        0.949999988079071,
        0.949999988079071,
        0.949999988079071,
        0.949999988079071,
        0.949999988079071,
        0.949999988079071,
        0.949999988079071,
        0.949999988079071,
        0.949999988079071,
        0.949999988079071,
        0.949999988079071
      ],
      "beta": [
        0.5,
        0.5,
        0.5,
        0.5,
        0.5,
        0.5,
        0.5,
        0.5,
        0.5,
        0.5,
        0.5,
        0.5,
        0.5,
        0.5,
        0.5,
        0.5,
        0.5,
        0.5,
        0.5,
        0.5,
        0.5,
        0.5,
        0.5,
        0.5,
        0.5,
        0.5,
        0.5,
        0.5,
        0.5,
        0.5,
        0.5,
        0.5
      ],
      "igain": [
        1.0,
        1.0,
        1.0,
        1.0,
        1.0,
        1.0,
        1.0,
        1.0,
        1.0,
        1.0,
        1.0,
        1.0,
        1.0,
        1.0,
        1.0,
        1.0,
        1.0,
        1.0,
        1.0,
        1.0,
        1.0,
        1.0,
        1.0,
        1.0,
        1.0,
        1.0,
        1.0,
        1.0,
        1.0,
        1.0,
        1.0,
        1.0
      ],
      "gamma": [
        0.5,
        0.5,
        0.5,
        0.5,
        0.5,
        0.5,
        0.5,
        0.5,
        0.5,
        0.5,
        0.5,
        0.5,
        0.5,
        0.5,
        0.5,
        0.5,
        0.5,
        0.5,
        0.5,
        0.5,
        0.5,
        0.5,
        0.5,
        0.5,
        0.5,
        0.5,
        0.5,
        0.5,
        0.5,
        0.5,
        0.5,
        0.5
      ],
      "eig_along": [
        0.44999998807907104,
        0.44999998807907104,
        0.44999998807907104,
        0.44999998807907104,
        0.44999998807907104,
        0.44999998807907104,
        0.44999998807907104,
        0.44999998807907104,
        0.44999998807907104,
        0.44999998807907104,
        0.44999998807907104,
        0.44999998807907104,
        0.44999998807907104,
        0.44999998807907104,
        0.44999998807907104,
        0.44999998807907104,
        0.44999998807907104,
        0.44999998807907104,
        0.44999998807907104,
        0.44999998807907104,
        0.44999998807907104,
        0.44999998807907104,
        0.44999998807907104,
        0.44999998807907104,
        0.44999998807907104,
        0.44999998807907104,
        0.44999998807907104,
        0.44999998807907104,
        0.44999998807907104,
        0.44999998807907104,
        0.44999998807907104,
        0.44999998807907104
      ]
    }
  ],
  "final_acc": 0.66522216796875,
  "final_loss": 0.7017655484378338,
  "unified_knobs": [
    {
      "layer": 0,
      "knob_mode": "learned",
      "preset": null,
      "phi_mode": 2,
      "lambda": [
        0.9302456378936768,
        0.8878074884414673,
        0.8631904721260071,
        0.9125062823295593,
        0.903991162776947,
        0.9024608135223389,
        0.9136080741882324,
        0.8866009712219238,
        0.8967360258102417,
        0.9215308427810669,
        0.8920964598655701,
        0.9055795669555664,
        0.8974665403366089,
        0.8851702809333801,
        0.9045544862747192,
        0.92686927318573,
        0.9377734661102295,
        0.9221761226654053,
        0.9179596900939941,
        0.8801981210708618,
        0.9193240404129028,
        0.9169402122497559,
        0.887238085269928,
        0.8962302207946777,
        0.8811816573143005,
        0.8874138593673706,
        0.9201412200927734,
        0.8786131739616394,
        0.9010788202285767,
        0.8951553106307983,
        0.8915757536888123,
        0.9020124673843384
      ],
      "beta": [
        0.5390192866325378,
        0.6441264748573303,
        0.6495832204818726,
        0.550102174282074,
        0.5615754723548889,
        0.552570104598999,
        0.5818760395050049,
        0.6226373910903931,
        0.6223634481430054,
        0.5271612405776978,
        0.6301310062408447,
        0.624183714389801,
        0.5991143584251404,
        0.6425977349281311,
        0.5939527750015259,
        0.5278153419494629,
        0.5164315104484558,
        0.5677083730697632,
        0.5686690807342529,
        0.6396914720535278,
        0.5683015584945679,
        0.5830481052398682,
        0.6315861344337463,
        0.5608724355697632,
        0.6308301091194153,
        0.5895775556564331,
        0.5450575351715088,
        0.6399388313293457,
        0.6108422875404358,
        0.6310864090919495,
        0.6384427547454834,
        0.580694317817688
      ],
      "igain": [
        1.0155465602874756,
        1.021472454071045,
        1.0762133598327637,
        1.0260647535324097,
        1.0273810625076294,
        1.0494697093963623,
        1.0365628004074097,
        1.0355055332183838,
        1.0566438436508179,
        1.022933006286621,
        1.0095696449279785,
        1.0365196466445923,
        1.036519169807434,
        1.0323898792266846,
        1.0356035232543945,
        1.025633692741394,
        1.0279937982559204,
        1.0128787755966187,
        1.0292373895645142,
        1.0253841876983643,
        1.0427743196487427,
        1.0206187963485718,
        1.038989782333374,
        1.0654398202896118,
        1.0342456102371216,
        1.0421373844146729,
        1.0313239097595215,
        1.0470162630081177,
        1.0524266958236694,
        1.02273690700531,
        1.0207219123840332,
        1.0472837686538696
      ],
      "gamma": [
        0.43269670009613037,
        0.38956186175346375,
        0.3995138108730316,
        0.4229651987552643,
        0.4223734140396118,
        0.42797911167144775,
        0.4258417785167694,
        0.391907662153244,
        0.39455512166023254,
        0.4212006628513336,
        0.3987809717655182,
        0.39406347274780273,
        0.38644230365753174,
        0.39350736141204834,
        0.40585795044898987,
        0.4167865514755249,
        0.42997944355010986,
        0.41042035818099976,
        0.3873307406902313,
        0.39208653569221497,
        0.423801064491272,
        0.40977734327316284,
        0.3912953734397888,
        0.44468384981155396,
        0.3872486352920532,
        0.38907507061958313,
        0.4235297739505768,
        0.4202156066894531,
        0.41058555245399475,
        0.39746958017349243,
        0.39134544134140015,
        0.44906896352767944
      ],
      "eig_along": [
        0.3912263512611389,
        0.24368101358413696,
        0.21360725164413452,
        0.36240410804748535,
        0.3424156904220581,
        0.34989070892333984,
        0.33173203468322754,
        0.26396358013153076,
        0.27437257766723633,
        0.39436960220336914,
        0.26196545362472534,
        0.2813958525657654,
        0.2983521819114685,
        0.24257254600524902,
        0.31060171127319336,
        0.3990539312362671,
        0.4213419556617737,
        0.3544677495956421,
        0.3492906093597412,
        0.24050664901733398,
        0.35102248191833496,
        0.3338921070098877,
        0.25565195083618164,
        0.33535778522491455,
        0.25035154819488525,
        0.2978363037109375,
        0.37508368492126465,
        0.2386743426322937,
        0.29023653268814087,
        0.2640689015388489,
        0.25313299894332886,
        0.3213181495666504
      ]
    },
    {
      "layer": 1,
      "knob_mode": "learned",
      "preset": null,
      "phi_mode": 2,
      "lambda": [
        0.8819734454154968,
        0.8982505202293396,
        0.8962488174438477,
        0.88514244556427,
        0.9076414108276367,
        0.8910854458808899,
        0.8907678723335266,
        0.8989396095275879,
        0.9169101715087891,
        0.9124959111213684,
        0.8915717601776123,
        0.884770393371582,
        0.9043856859207153,
        0.8937415480613708,
        0.8902157545089722,
        0.8942617177963257,
        0.9027619957923889,
        0.8994430303573608,
        0.8956287503242493,
        0.8984775543212891,
        0.902481198310852,
        0.8891633749008179,
        0.8886535167694092,
        0.8934557437896729,
        0.9063936471939087,
        0.8990116119384766,
        0.8972848653793335,
        0.8765149712562561,
        0.8873354196548462,
        0.8805228471755981,
        0.9016306400299072,
        0.8831745386123657
      ],
      "beta": [
        0.6228811144828796,
        0.6005188226699829,
        0.5556237697601318,
        0.634643018245697,
        0.6260814070701599,
        0.6331925988197327,
        0.6359689235687256,
        0.6345884203910828,
        0.6154009699821472,
        0.6159352660179138,
        0.6389784216880798,
        0.5623995065689087,
        0.6231597661972046,
        0.6433436870574951,
        0.6223942041397095,
        0.6291844248771667,
        0.6107088923454285,
        0.6266462802886963,
        0.5985604524612427,
        0.6198193430900574,
        0.6411246657371521,
        0.6203582882881165,
        0.6225139498710632,
        0.6362890005111694,
        0.6192970275878906,
        0.636410117149353,
        0.6187566518783569,
        0.6452274918556213,
        0.5838245153427124,
        0.6124555468559265,
        0.62919682264328,
        0.648531436920166
      ],
      "igain": [
        1.0301592350006104,
        1.025238275527954,
        1.070999264717102,
        1.030283808708191,
        1.0235724449157715,
        1.0148587226867676,
        1.0252450704574585,
        1.032049536705017,
        1.0199100971221924,
        1.0180063247680664,
        1.0220671892166138,
        1.0421297550201416,
        1.0108052492141724,
        1.02330482006073,
        1.043528437614441,
        1.0166412591934204,
        1.0325267314910889,
        1.0156383514404297,
        1.0075604915618896,
        1.0401850938796997,
        1.018702507019043,
        1.0396312475204468,
        1.0319586992263794,
        1.023905873298645,
        1.0103976726531982,
        1.0087450742721558,
        1.0249840021133423,
        1.0300004482269287,
        1.0324487686157227,
        1.0155284404754639,
        1.0258225202560425,
        1.0173333883285522
      ],
      "gamma": [
        0.3830508291721344,
        0.3930332660675049,
        0.479701429605484,
        0.38011807203292847,
        0.41046005487442017,
        0.39192995429039,
        0.3908936679363251,
        0.39120182394981384,
        0.4085797071456909,
        0.4052495062351227,
        0.3873277008533478,
        0.41307178139686584,
        0.4051760137081146,
        0.384337455034256,
        0.3880917429924011,
        0.3980424404144287,
        0.38979673385620117,
        0.4128866493701935,
        0.4194510877132416,
        0.38986876606941223,
        0.3826223909854889,
        0.38850104808807373,
        0.3887353837490082,
        0.38792678713798523,
        0.4039933979511261,
        0.39598843455314636,
        0.3970568776130676,
        0.3824998140335083,
        0.42450156807899475,
        0.4171494245529175,
        0.39583534002304077,
        0.3837125897407532
      ],
      "eig_along": [
        0.2590923309326172,
        0.2977316975593567,
        0.3406250476837158,
        0.250499427318573,
        0.2815600037574768,
        0.2578928470611572,
        0.254798948764801,
        0.2643511891365051,
        0.30150920152664185,
        0.2965606451034546,
        0.25259333848953247,
        0.32237088680267334,
        0.28122591972351074,
        0.25039786100387573,
        0.2678215503692627,
        0.26507729291915894,
        0.29205310344696045,
        0.27279675006866455,
        0.2970682978630066,
        0.2786582112312317,
        0.26135653257369995,
        0.2688050866127014,
        0.26613956689834595,
        0.2571667432785034,
        0.28709661960601807,
        0.26260149478912354,
        0.27852821350097656,
        0.23128747940063477,
        0.3035109043121338,
        0.26806730031967163,
        0.2724338173866272,
        0.2346431016921997
      ]
    },
    {
      "layer": 2,
      "knob_mode": "learned",
      "preset": null,
      "phi_mode": 2,
      "lambda": [
        0.8966394066810608,
        0.925284743309021,
        0.9005550742149353,
        0.8958327770233154,
        0.9127169847488403,
        0.8994761109352112,
        0.8843609690666199,
        0.8965933322906494,
        0.9063453674316406,
        0.9073238372802734,
        0.903464674949646,
        0.898690938949585,
        0.8730894327163696,
        0.8871186971664429,
        0.8806947469711304,
        0.9168661832809448,
        0.9080332517623901,
        0.9126012325286865,
        0.889467179775238,
        0.8975560665130615,
        0.8977996110916138,
        0.8880795240402222,
        0.8913949728012085,
        0.8950802087783813,
        0.9038808345794678,
        0.9019812941551208,
        0.8922150135040283,
        0.8953419327735901,
        0.8912856578826904,
        0.8805160522460938,
        0.9006658792495728,
        0.9054582118988037
      ],
      "beta": [
        0.6160064935684204,
        0.58970707654953,
        0.6135626435279846,
        0.609732449054718,
        0.6236683130264282,
        0.5987262725830078,
        0.6004890203475952,
        0.6260619759559631,
        0.6013683676719666,
        0.6061586737632751,
        0.6175640821456909,
        0.6283324956893921,
        0.6428722739219666,
        0.6223220229148865,
        0.639013946056366,
        0.5940526723861694,
        0.6030390858650208,
        0.6362860202789307,
        0.6292835474014282,
        0.6274832487106323,
        0.6212690472602844,
        0.6379555463790894,
        0.5758450627326965,
        0.6419234275817871,
        0.6106342673301697,
        0.6423633098602295,
        0.6271051168441772,
        0.6417660713195801,
        0.6276180744171143,
        0.6406700611114502,
        0.594969630241394,
        0.6401278972625732
      ],
      "igain": [
        1.0130847692489624,
        1.0189828872680664,
        1.0229172706604004,
        1.0132962465286255,
        1.0122592449188232,
        1.0146905183792114,
        1.0379198789596558,
        1.012465000152588,
        1.0215989351272583,
        1.012239933013916,
        1.0196195840835571,
        1.0247695446014404,
        1.051131248474121,
        1.0398207902908325,
        1.0285509824752808,
        1.0007221698760986,
        1.0150823593139648,
        1.0177204608917236,
        1.0116143226623535,
        1.0005401372909546,
        1.0279834270477295,
        1.0259920358657837,
        1.0600684881210327,
        1.0327621698379517,
        1.0131423473358154,
        1.0274631977081299,
        1.0204397439956665,
        1.0077179670333862,
        1.0139546394348145,
        1.0478216409683228,
        1.0217164754867554,
        1.0362544059753418
      ],
      "gamma": [
        0.393466055393219,
        0.4018903374671936,
        0.41072070598602295,
        0.3971811532974243,
        0.4153115153312683,
        0.4105505645275116,
        0.45241019129753113,
        0.3863959014415741,
        0.41569963097572327,
        0.4131224751472473,
        0.4159586429595947,
        0.3818451464176178,
        0.38076266646385193,
        0.4003222584724426,
        0.3848486542701721,
        0.4129200577735901,
        0.3999001681804657,
        0.39417028427124023,
        0.3884541988372803,
        0.40776997804641724,
        0.39055198431015015,
        0.3869855999946594,
        0.4181040823459625,
        0.38719451427459717,
        0.3970455527305603,
        0.39577314257621765,
        0.39056238532066345,
        0.40271320939064026,
        0.3794913589954376,
        0.386425644159317,
        0.42028066515922546,
        0.39588940143585205
      ],
      "eig_along": [
        0.2806329131126404,
        0.33557766675949097,
        0.2869924306869507,
        0.2861003279685974,
        0.2890486717224121,
        0.30074983835220337,
        0.28387194871902466,
        0.2705313563346863,
        0.3049769997596741,
        0.3011651635169983,
        0.2859005928039551,
        0.27035844326019287,
        0.23021715879440308,
        0.2647966742515564,
        0.2416808009147644,
        0.3228135108947754,
        0.3049941658973694,
        0.27631521224975586,
        0.2601836323738098,
        0.2700728178024292,
        0.27653056383132935,
        0.2501239776611328,
        0.31554991006851196,
        0.25315678119659424,
        0.2932465672492981,
        0.25961798429489136,
        0.2651098966598511,
        0.25357586145401,
        0.26366758346557617,
        0.23984599113464355,
        0.3056962490081787,
        0.26533031463623047
      ]
    },
    {
      "layer": 3,
      "knob_mode": "learned",
      "preset": null,
      "phi_mode": 2,
      "lambda": [
        0.908318817615509,
        0.8987460136413574,
        0.9222792387008667,
        0.9024499654769897,
        0.9045242071151733,
        0.9250495433807373,
        0.8966699838638306,
        0.8806487321853638,
        0.9320037961006165,
        0.9154956936836243,
        0.89764004945755,
        0.9071786403656006,
        0.9377204775810242,
        0.8851620554924011,
        0.8765468001365662,
        0.9031339883804321,
        0.921433687210083,
        0.917709231376648,
        0.8704782724380493,
        0.9183016419410706,
        0.8762925267219543,
        0.9248987436294556,
        0.934349775314331,
        0.9052184820175171,
        0.9069066047668457,
        0.9144757390022278,
        0.9075420498847961,
        0.9128062725067139,
        0.8921924829483032,
        0.8968226909637451,
        0.9357326030731201,
        0.9284915328025818
      ],
      "beta": [
        0.6083572506904602,
        0.6213990449905396,
        0.6069035530090332,
        0.6167724132537842,
        0.6199631094932556,
        0.5700494050979614,
        0.6247998476028442,
        0.6275748610496521,
        0.60065758228302,
        0.6210267543792725,
        0.6285684704780579,
        0.5751989483833313,
        0.5871285796165466,
        0.6207855939865112,
        0.6576648950576782,
        0.5870302319526672,
        0.5792416930198669,
        0.6029521822929382,
        0.6539114713668823,
        0.6112241148948669,
        0.6512848138809204,
        0.6227721571922302,
        0.6404036283493042,
        0.6298942565917969,
        0.6174358129501343,
        0.6175087690353394,
        0.6248714923858643,
        0.6039084196090698,
        0.6197996735572815,
        0.618486762046814,
        0.5700583457946777,
        0.5365804433822632
      ],
      "igain": [
        1.0070831775665283,
        1.037519097328186,
        1.001642107963562,
        1.002279281616211,
        0.9961870312690735,
        1.0046699047088623,
        1.0028553009033203,
        1.0065827369689941,
        1.0061061382293701,
        1.0079950094223022,
        1.015761375427246,
        1.0446799993515015,
        1.003453254699707,
        1.0136359930038452,
        1.030311107635498,
        1.0145379304885864,
        0.9998729228973389,
        1.0110479593276978,
        1.0041338205337524,
        0.9937580823898315,
        1.0247783660888672,
        0.9951381087303162,
        1.0049898624420166,
        0.996046245098114,
        1.0138534307479858,
        1.0048924684524536,
        1.0180878639221191,
        1.0232667922973633,
        1.0046892166137695,
        1.002586007118225,
        0.9995519518852234,
        1.015089750289917
      ],
      "gamma": [
        0.4065341651439667,
        0.39283639192581177,
        0.39960891008377075,
        0.4009736180305481,
        0.3943428695201874,
        0.4421011805534363,
        0.4009243845939636,
        0.3996530771255493,
        0.42174553871154785,
        0.40069493651390076,
        0.3974040448665619,
        0.4976019263267517,
        0.4226166903972626,
        0.3968225419521332,
        0.39367374777793884,
        0.40493202209472656,
        0.4138314723968506,
        0.43068480491638184,
        0.3891555070877075,
        0.404482364654541,
        0.37761619687080383,
        0.40580466389656067,
        0.4073425829410553,
        0.39808499813079834,
        0.4022134840488434,
        0.40696030855178833,
        0.39394718408584595,
        0.4225786030292511,
        0.4037826955318451,
        0.4057598114013672,
        0.4586420953273773,
        0.4338376224040985
      ],
      "eig_along": [
        0.29996156692504883,
        0.27734696865081787,
        0.3153756856918335,
        0.28567755222320557,
        0.2845610976219177,
        0.3550001382827759,
        0.27187013626098633,
        0.25307387113571167,
        0.33134621381759644,
        0.2944689393043518,
        0.2690715789794922,
        0.3319796919822693,
        0.35059189796447754,
        0.2643764615058899,
        0.21888190507888794,
        0.3161037564277649,
        0.34219199419021606,
        0.3147570490837097,
        0.216566801071167,
        0.3070775270462036,
        0.22500771284103394,
        0.30212658643722534,
        0.29394614696502686,
        0.2753242254257202,
        0.2894707918167114,
        0.2969669699668884,
        0.2826705574989319,
        0.30889785289764404,
        0.27239280939102173,
        0.27833592891693115,
        0.3656742572784424,
        0.3919110894203186
      ]
    }
  ],
  "spec_reg_final": 0.5556573271751404,
  "elapsed_total_s": 117.20617270469666,
  "length_extrap": {
    "128": {
      "acc": 0.670867919921875,
      "loss": 0.6932771056890488,
      "B_eval": 32
    },
    "256": {
      "acc": 0.6586761474609375,
      "loss": 0.7085365951061249,
      "B_eval": 32
    },
    "512": {
      "acc": 0.6583480834960938,
      "loss": 0.7136333510279655,
      "B_eval": 32
    },
    "1024": {
      "acc": 0.65740966796875,
      "loss": 0.7150591313838959,
      "B_eval": 16
    }
  }
}