{
  "task": "mqar_recall",
  "pattern": [
    "typed-gdn2",
    "typed-gdn2",
    "typed-gdn2",
    "typed-gdn2"
  ],
  "dim": 256,
  "depth": 4,
  "seq_len": 128,
  "batch_size": 32,
  "lr": 0.0005,
  "seed": 123,
  "params": 8575232,
  "mlp_ratio": 2.0,
  "disable_autocast": true,
  "use_triton_e88": false,
  "linear_state": null,
  "state_activation": null,
  "use_gate": null,
  "decay_mode": null,
  "gdn_allow_neg_eigval": 1,
  "e88_pos_eigval_clamp": null,
  "e88_raw_write": null,
  "knob_lr_mult": 1.0,
  "lam_max": null,
  "beta_max": null,
  "igain_max": null,
  "corner_mixture": null,
  "head_type_logits": "-1.791759,-1.791759,-1.791759,-1.791759,-1.791759,-30.000000,-30.000000,-30.000000,-1.791759",
  "refit_has_mom": 0,
  "refit_newton_steps": null,
  "phi": null,
  "split_edit": null,
  "cplx_real_only": null,
  "cplx_nonlin_subset_frac": null,
  "cplx_nonlin_subset_phi": null,
  "cplx_dc_frac": null,
  "cplx_force_sequential": null,
  "typed_alloc": {
    "type_names": [
      "gdn2_recall",
      "e97_track",
      "count",
      "latch",
      "nonlin",
      "gdn2_nonlin_shell",
      "e97_raw",
      "e97_delta",
      "refit"
    ],
    "fractions": {
      "gdn2_recall": 0.1666666666666199,
      "e97_track": 0.1666666666666199,
      "count": 0.1666666666666199,
      "latch": 0.1666666666666199,
      "nonlin": 0.1666666666666199,
      "gdn2_nonlin_shell": 9.357618577979344e-14,
      "e97_raw": 9.357618577979344e-14,
      "e97_delta": 9.357618577979344e-14,
      "refit": 0.1666666666666199
    },
    "counts": {
      "gdn2_recall": 6,
      "e97_track": 6,
      "count": 5,
      "latch": 5,
      "nonlin": 5,
      "gdn2_nonlin_shell": 0,
      "e97_raw": 0,
      "e97_delta": 0,
      "refit": 5
    },
    "n_gdn": 6,
    "n_unified": 21,
    "unified_counts": [
      6,
      5,
      5,
      5
    ],
    "n_shell": 0,
    "n_e97_raw": 0,
    "n_e97_delta": 0,
    "n_refit": 5
  },
  "spec_reg": null,
  "spec_reg_weight": 1.0,
  "spec_reg_anneal": 0.5,
  "curriculum": null,
  "random_baseline_acc": 0.015625,
  "steps": [
    {
      "step": 0,
      "train_loss": 175.1132049560547,
      "eval_acc": 0.017578125,
      "eval_loss": 166.36753845214844,
      "elapsed_s": 111.06640768051147
    },
    {
      "step": 600,
      "train_loss": 3.233478307723999,
      "eval_acc": 0.0986328125,
      "eval_loss": 3.258374035358429,
      "elapsed_s": 177.87673234939575
    },
    {
      "step": 1200,
      "train_loss": 2.535158634185791,
      "eval_acc": 0.1611328125,
      "eval_loss": 2.6351687908172607,
      "elapsed_s": 244.7251672744751
    },
    {
      "step": 1800,
      "train_loss": 2.452255964279175,
      "eval_acc": 0.16796875,
      "eval_loss": 2.444687843322754,
      "elapsed_s": 311.2764801979065
    },
    {
      "step": 2400,
      "train_loss": 2.1591734886169434,
      "eval_acc": 0.2109375,
      "eval_loss": 2.2455608248710632,
      "elapsed_s": 377.85853838920593
    },
    {
      "step": 3000,
      "train_loss": 0.9930704236030579,
      "eval_acc": 0.4970703125,
      "eval_loss": 1.4526095688343048,
      "elapsed_s": 444.40201139450073
    },
    {
      "step": 3600,
      "train_loss": 0.2879970669746399,
      "eval_acc": 0.8193359375,
      "eval_loss": 0.5215627178549767,
      "elapsed_s": 510.7809271812439
    },
    {
      "step": 4200,
      "train_loss": 0.14057806134223938,
      "eval_acc": 0.9560546875,
      "eval_loss": 0.13766304776072502,
      "elapsed_s": 576.9357559680939
    },
    {
      "step": 4800,
      "train_loss": 0.0038233508821576834,
      "eval_acc": 0.984375,
      "eval_loss": 0.04554606229066849,
      "elapsed_s": 643.3110918998718
    },
    {
      "step": 5400,
      "train_loss": 0.014026272110641003,
      "eval_acc": 0.9990234375,
      "eval_loss": 0.005122747097630054,
      "elapsed_s": 710.1994354724884
    },
    {
      "step": 6000,
      "train_loss": 0.0031908699311316013,
      "eval_acc": 0.998046875,
      "eval_loss": 0.007111194820026867,
      "elapsed_s": 776.6258609294891
    },
    {
      "step": 6600,
      "train_loss": 0.00029134342912584543,
      "eval_acc": 1.0,
      "eval_loss": 0.000761487155159557,
      "elapsed_s": 843.1491420269012
    },
    {
      "step": 7200,
      "train_loss": 1.8014661691267975e-05,
      "eval_acc": 0.9990234375,
      "eval_loss": 0.0019142998389725108,
      "elapsed_s": 909.7932951450348
    },
    {
      "step": 7800,
      "train_loss": 2.178083832404809e-06,
      "eval_acc": 1.0,
      "eval_loss": 1.9213176983612357e-05,
      "elapsed_s": 976.594651222229
    },
    {
      "step": 8400,
      "train_loss": 0.00011181269655935466,
      "eval_acc": 1.0,
      "eval_loss": 1.7486400281541137e-05,
      "elapsed_s": 1043.4173641204834
    },
    {
      "step": 9000,
      "train_loss": 1.0304680472472683e-05,
      "eval_acc": 1.0,
      "eval_loss": 3.1721897983061353e-05,
      "elapsed_s": 1100.9943339824677
    },
    {
      "step": 9600,
      "train_loss": 2.3483458789996803e-05,
      "eval_acc": 0.9990234375,
      "eval_loss": 0.001036232331074416,
      "elapsed_s": 1161.2217619419098
    },
    {
      "step": 10200,
      "train_loss": 5.4059437388787046e-05,
      "eval_acc": 1.0,
      "eval_loss": 0.0006551954714257846,
      "elapsed_s": 1228.4228301048279
    },
    {
      "step": 10800,
      "train_loss": 2.1496725821634755e-05,
      "eval_acc": 1.0,
      "eval_loss": 3.865412676162805e-05,
      "elapsed_s": 1295.7566046714783
    },
    {
      "step": 11400,
      "train_loss": 0.00023213852546177804,
      "eval_acc": 1.0,
      "eval_loss": 3.177433117507178e-06,
      "elapsed_s": 1362.8644692897797
    },
    {
      "step": 11999,
      "train_loss": 3.441112710333982e-07,
      "eval_acc": 1.0,
      "eval_loss": 0.00013361609717321699,
      "elapsed_s": 1430.3971173763275
    }
  ],
  "final_acc": 0.999755859375,
  "final_loss": 0.0006315224482844606,
  "elapsed_total_s": 1431.6875538825989,
  "length_extrap": {
    "128": {
      "acc": 1.0,
      "loss": 8.880198341110201e-07,
      "B_eval": 32
    },
    "256": {
      "acc": 0.991455078125,
      "loss": 0.029031366168055683,
      "B_eval": 32
    },
    "512": {
      "acc": 0.804931640625,
      "loss": 1.2071112096309662,
      "B_eval": 32
    }
  }
}