{
  "task": "anbncn_viability",
  "pattern": [
    "typed-gdn2",
    "typed-gdn2",
    "typed-gdn2",
    "typed-gdn2"
  ],
  "dim": 256,
  "depth": 4,
  "seq_len": 128,
  "batch_size": 32,
  "lr": 0.0003,
  "seed": 123,
  "params": 7375104,
  "disable_autocast": false,
  "use_triton_e88": false,
  "linear_state": null,
  "state_activation": null,
  "use_gate": null,
  "decay_mode": null,
  "gdn_allow_neg_eigval": 1,
  "e88_pos_eigval_clamp": null,
  "e88_raw_write": null,
  "knob_lr_mult": 1.0,
  "lam_max": null,
  "beta_max": null,
  "igain_max": null,
  "corner_mixture": null,
  "head_type_logits": "-30.0,-30.0,-30.0,-30.0,-30.0,-30.0,0.0,-30.0",
  "typed_alloc": {
    "type_names": [
      "gdn2_recall",
      "e97_track",
      "count",
      "latch",
      "nonlin",
      "gdn2_nonlin_shell",
      "e97_raw",
      "e97_delta"
    ],
    "fractions": {
      "gdn2_recall": 9.357622968834046e-14,
      "e97_track": 9.357622968834046e-14,
      "count": 9.357622968834046e-14,
      "latch": 9.357622968834046e-14,
      "nonlin": 9.357622968834046e-14,
      "gdn2_nonlin_shell": 9.357622968834046e-14,
      "e97_raw": 0.999999999999345,
      "e97_delta": 9.357622968834046e-14
    },
    "counts": {
      "gdn2_recall": 0,
      "e97_track": 0,
      "count": 0,
      "latch": 0,
      "nonlin": 0,
      "gdn2_nonlin_shell": 0,
      "e97_raw": 32,
      "e97_delta": 0
    },
    "n_gdn": 0,
    "n_unified": 0,
    "unified_counts": [
      0,
      0,
      0,
      0
    ],
    "n_shell": 0,
    "n_e97_raw": 32,
    "n_e97_delta": 0
  },
  "spec_reg": null,
  "spec_reg_weight": 1.0,
  "spec_reg_anneal": 0.5,
  "curriculum": null,
  "random_baseline_acc": 0.5,
  "steps": [
    {
      "step": 0,
      "train_loss": 170.36441040039062,
      "eval_acc": 0.33349609375,
      "eval_loss": 152.52011108398438,
      "elapsed_s": 5.446224689483643
    },
    {
      "step": 250,
      "train_loss": 0.12347723543643951,
      "eval_acc": 0.93670654296875,
      "eval_loss": 0.10095148347318172,
      "elapsed_s": 13.652950048446655
    },
    {
      "step": 500,
      "train_loss": 0.08750736713409424,
      "eval_acc": 0.9251708984375,
      "eval_loss": 0.09613083675503731,
      "elapsed_s": 20.85453176498413
    },
    {
      "step": 750,
      "train_loss": 0.0836058259010315,
      "eval_acc": 0.95257568359375,
      "eval_loss": 0.09494191035628319,
      "elapsed_s": 28.211028337478638
    },
    {
      "step": 1000,
      "train_loss": 0.09262807667255402,
      "eval_acc": 0.934814453125,
      "eval_loss": 0.10097393579781055,
      "elapsed_s": 35.659202575683594
    },
    {
      "step": 1250,
      "train_loss": 0.08777253329753876,
      "eval_acc": 0.96441650390625,
      "eval_loss": 0.06947962194681168,
      "elapsed_s": 42.88193130493164
    },
    {
      "step": 1500,
      "train_loss": 0.08228699862957001,
      "eval_acc": 0.9652099609375,
      "eval_loss": 0.06342137046158314,
      "elapsed_s": 50.48661541938782
    },
    {
      "step": 1750,
      "train_loss": 0.025154169648885727,
      "eval_acc": 0.98162841796875,
      "eval_loss": 0.039300494361668825,
      "elapsed_s": 57.91255164146423
    },
    {
      "step": 2000,
      "train_loss": 0.04097248613834381,
      "eval_acc": 0.98028564453125,
      "eval_loss": 0.037916187196969986,
      "elapsed_s": 65.12529516220093
    },
    {
      "step": 2250,
      "train_loss": 0.02559775859117508,
      "eval_acc": 0.976806640625,
      "eval_loss": 0.0391221041791141,
      "elapsed_s": 72.92756605148315
    },
    {
      "step": 2500,
      "train_loss": 0.07034385949373245,
      "eval_acc": 0.98907470703125,
      "eval_loss": 0.02033982053399086,
      "elapsed_s": 80.25375270843506
    },
    {
      "step": 2750,
      "train_loss": 0.012757835909724236,
      "eval_acc": 0.98541259765625,
      "eval_loss": 0.031528386287391186,
      "elapsed_s": 87.3559398651123
    },
    {
      "step": 3000,
      "train_loss": 0.020107025280594826,
      "eval_acc": 0.9884033203125,
      "eval_loss": 0.02020677295513451,
      "elapsed_s": 94.7608208656311
    },
    {
      "step": 3250,
      "train_loss": 0.005970521830022335,
      "eval_acc": 0.99005126953125,
      "eval_loss": 0.019091739552095532,
      "elapsed_s": 101.8996970653534
    },
    {
      "step": 3500,
      "train_loss": 0.09313561022281647,
      "eval_acc": 0.997314453125,
      "eval_loss": 0.00736581307137385,
      "elapsed_s": 109.14271354675293
    },
    {
      "step": 3750,
      "train_loss": 0.20662817358970642,
      "eval_acc": 0.99566650390625,
      "eval_loss": 0.009538473736029118,
      "elapsed_s": 116.44604420661926
    },
    {
      "step": 4000,
      "train_loss": 0.014684217981994152,
      "eval_acc": 0.99871826171875,
      "eval_loss": 0.003425658884225413,
      "elapsed_s": 123.59263753890991
    },
    {
      "step": 4250,
      "train_loss": 0.0022771370131522417,
      "eval_acc": 0.999755859375,
      "eval_loss": 0.0015602753846906126,
      "elapsed_s": 130.82062792778015
    },
    {
      "step": 4500,
      "train_loss": 0.03599884361028671,
      "eval_acc": 0.99951171875,
      "eval_loss": 0.003204731794539839,
      "elapsed_s": 138.11935186386108
    },
    {
      "step": 4750,
      "train_loss": 0.005985606461763382,
      "eval_acc": 0.99957275390625,
      "eval_loss": 0.0014228820364223793,
      "elapsed_s": 145.34059953689575
    },
    {
      "step": 4999,
      "train_loss": 0.00047949751024134457,
      "eval_acc": 0.99957275390625,
      "eval_loss": 0.001660493333474733,
      "elapsed_s": 151.76038002967834
    }
  ],
  "final_acc": 0.999664306640625,
  "final_loss": 0.0010198758336628089,
  "elapsed_total_s": 154.12688493728638,
  "length_extrap": {
    "128": {
      "acc": 0.999725341796875,
      "loss": 0.00221362744923681,
      "B_eval": 32
    },
    "256": {
      "acc": 0.9141845703125,
      "loss": 3.3949625194072723,
      "B_eval": 32
    },
    "512": {
      "acc": 0.8465957641601562,
      "loss": 10.01018089056015,
      "B_eval": 32
    },
    "1024": {
      "acc": 0.8253326416015625,
      "loss": 12.992534875869751,
      "B_eval": 16
    }
  }
}