{
  "task": "mqar_recall",
  "pattern": [
    "fla-gdn",
    "fla-gdn",
    "fla-gdn",
    "fla-gdn"
  ],
  "dim": 256,
  "depth": 4,
  "seq_len": 128,
  "batch_size": 32,
  "lr": 0.001,
  "seed": 456,
  "params": 2919440,
  "mlp_ratio": 2.0,
  "disable_autocast": false,
  "use_triton_e88": false,
  "linear_state": null,
  "state_activation": null,
  "use_gate": null,
  "decay_mode": null,
  "gdn_allow_neg_eigval": 1,
  "gdn_use_conv": null,
  "e88_pos_eigval_clamp": null,
  "e88_raw_write": null,
  "knob_lr_mult": 1.0,
  "lam_max": null,
  "beta_max": null,
  "igain_max": null,
  "corner_mixture": null,
  "head_type_logits": null,
  "refit_has_mom": null,
  "refit_newton_steps": null,
  "phi": null,
  "split_edit": null,
  "cplx_real_only": null,
  "cplx_nonlin_subset_frac": null,
  "cplx_nonlin_subset_phi": null,
  "cplx_dc_frac": null,
  "cplx_force_sequential": null,
  "typed_alloc": null,
  "spec_reg": null,
  "spec_reg_weight": 1.0,
  "spec_reg_anneal": 0.5,
  "curriculum": null,
  "random_baseline_acc": 0.015625,
  "steps": [
    {
      "step": 0,
      "train_loss": 240.82171630859375,
      "eval_acc": 0.0205078125,
      "eval_loss": 229.41350173950195,
      "elapsed_s": 5.987715721130371
    },
    {
      "step": 400,
      "train_loss": 2.92862606048584,
      "eval_acc": 0.166015625,
      "eval_loss": 2.9480573534965515,
      "elapsed_s": 20.47325897216797
    },
    {
      "step": 800,
      "train_loss": 0.423148512840271,
      "eval_acc": 0.78515625,
      "eval_loss": 0.7081622183322906,
      "elapsed_s": 34.05464291572571
    },
    {
      "step": 1200,
      "train_loss": 0.0661935955286026,
      "eval_acc": 0.966796875,
      "eval_loss": 0.11799097992479801,
      "elapsed_s": 47.72030472755432
    },
    {
      "step": 1600,
      "train_loss": 0.07291895896196365,
      "eval_acc": 0.986328125,
      "eval_loss": 0.055012413300573826,
      "elapsed_s": 61.48662519454956
    },
    {
      "step": 2000,
      "train_loss": 0.0487281009554863,
      "eval_acc": 0.9873046875,
      "eval_loss": 0.038540459237992764,
      "elapsed_s": 74.90751457214355
    },
    {
      "step": 2400,
      "train_loss": 0.007228906732052565,
      "eval_acc": 0.994140625,
      "eval_loss": 0.024144812021404505,
      "elapsed_s": 88.70011305809021
    },
    {
      "step": 2800,
      "train_loss": 0.0034173941239714622,
      "eval_acc": 0.9921875,
      "eval_loss": 0.01916466886177659,
      "elapsed_s": 102.29142260551453
    },
    {
      "step": 3200,
      "train_loss": 0.01612570695579052,
      "eval_acc": 0.9951171875,
      "eval_loss": 0.01479023095453158,
      "elapsed_s": 115.82363796234131
    },
    {
      "step": 3600,
      "train_loss": 0.022203223779797554,
      "eval_acc": 0.994140625,
      "eval_loss": 0.0221029159729369,
      "elapsed_s": 129.19729948043823
    },
    {
      "step": 4000,
      "train_loss": 0.0035392073914408684,
      "eval_acc": 0.994140625,
      "eval_loss": 0.015844542300328612,
      "elapsed_s": 143.07134222984314
    },
    {
      "step": 4400,
      "train_loss": 0.030626647174358368,
      "eval_acc": 0.9970703125,
      "eval_loss": 0.005211218711338006,
      "elapsed_s": 157.57823944091797
    },
    {
      "step": 4800,
      "train_loss": 0.015627166256308556,
      "eval_acc": 0.998046875,
      "eval_loss": 0.005202479238505475,
      "elapsed_s": 171.2849621772766
    },
    {
      "step": 5200,
      "train_loss": 0.016522053629159927,
      "eval_acc": 0.9990234375,
      "eval_loss": 0.0034333590156165883,
      "elapsed_s": 185.45572781562805
    },
    {
      "step": 5600,
      "train_loss": 0.001590715954080224,
      "eval_acc": 0.99609375,
      "eval_loss": 0.011806880007497966,
      "elapsed_s": 199.8315408229828
    },
    {
      "step": 6000,
      "train_loss": 0.0003515256103128195,
      "eval_acc": 0.9990234375,
      "eval_loss": 0.002928809219156392,
      "elapsed_s": 214.28243255615234
    },
    {
      "step": 6400,
      "train_loss": 0.030466176569461823,
      "eval_acc": 1.0,
      "eval_loss": 0.0015981426840880886,
      "elapsed_s": 228.46635460853577
    },
    {
      "step": 6800,
      "train_loss": 0.0010801786556839943,
      "eval_acc": 0.998046875,
      "eval_loss": 0.005194037741603097,
      "elapsed_s": 242.54055428504944
    },
    {
      "step": 7200,
      "train_loss": 0.00012759376841131598,
      "eval_acc": 1.0,
      "eval_loss": 0.0012645344977499917,
      "elapsed_s": 256.23018860816956
    },
    {
      "step": 7600,
      "train_loss": 0.00013787264470010996,
      "eval_acc": 0.99609375,
      "eval_loss": 0.016051001224695938,
      "elapsed_s": 269.7516379356384
    },
    {
      "step": 7999,
      "train_loss": 0.0029411925934255123,
      "eval_acc": 0.9990234375,
      "eval_loss": 0.003145557508105412,
      "elapsed_s": 283.15962767601013
    }
  ],
  "final_acc": 0.99853515625,
  "final_loss": 0.0043560314827573166,
  "elapsed_total_s": 283.4217150211334,
  "length_extrap": {
    "128": {
      "acc": 0.998046875,
      "loss": 0.004548547563899774,
      "B_eval": 32
    },
    "256": {
      "acc": 0.97802734375,
      "loss": 0.07522521214559674,
      "B_eval": 32
    },
    "512": {
      "acc": 0.8734130859375,
      "loss": 0.5378390625119209,
      "B_eval": 32
    }
  }
}