{
  "task": "flag_hold_recall",
  "pattern": [
    "typed-gdn2",
    "typed-gdn2",
    "typed-gdn2",
    "typed-gdn2"
  ],
  "dim": 248,
  "depth": 4,
  "seq_len": 128,
  "batch_size": 32,
  "lr": 0.0008429537809399478,
  "seed": 42,
  "params": 7912672,
  "disable_autocast": true,
  "use_triton_e88": false,
  "linear_state": null,
  "state_activation": null,
  "use_gate": null,
  "decay_mode": null,
  "gdn_allow_neg_eigval": null,
  "e88_pos_eigval_clamp": null,
  "e88_raw_write": null,
  "knob_lr_mult": 1.0,
  "lam_max": 1.585,
  "beta_max": 2.747,
  "igain_max": null,
  "corner_mixture": null,
  "head_type_logits": "3.279,-0.7433,-3.2953,-3.7057,-0.8381",
  "typed_alloc": {
    "type_names": [
      "gdn2_recall",
      "e97_track",
      "count",
      "latch",
      "nonlin"
    ],
    "fractions": {
      "gdn2_recall": 0.9647619388420311,
      "e97_track": 0.017280546264482388,
      "count": 0.0013465979508468305,
      "latch": 0.0008933126703698629,
      "nonlin": 0.015717604272269703
    },
    "counts": {
      "gdn2_recall": 46,
      "e97_track": 1,
      "count": 0,
      "latch": 0,
      "nonlin": 1
    },
    "n_gdn": 46,
    "n_unified": 2,
    "unified_counts": [
      1,
      0,
      0,
      1
    ]
  },
  "spec_reg": null,
  "spec_reg_weight": 1.0,
  "spec_reg_anneal": 0.5,
  "curriculum": null,
  "random_baseline_acc": 0.5,
  "steps": [
    {
      "step": 0,
      "train_loss": 187.056396484375,
      "eval_acc": 0.0,
      "eval_loss": 124.71511268615723,
      "elapsed_s": 3.802457571029663
    },
    {
      "step": 100,
      "train_loss": 0.0,
      "eval_acc": 1.0,
      "eval_loss": 3.725290076417309e-09,
      "elapsed_s": 7.878294944763184
    },
    {
      "step": 200,
      "train_loss": 0.0,
      "eval_acc": 1.0,
      "eval_loss": 0.0,
      "elapsed_s": 11.686239957809448
    },
    {
      "step": 300,
      "train_loss": 0.0,
      "eval_acc": 1.0,
      "eval_loss": 0.0,
      "elapsed_s": 15.384604454040527
    },
    {
      "step": 400,
      "train_loss": 0.0,
      "eval_acc": 1.0,
      "eval_loss": 0.0,
      "elapsed_s": 19.038236618041992
    },
    {
      "step": 500,
      "train_loss": 0.0,
      "eval_acc": 1.0,
      "eval_loss": 0.0,
      "elapsed_s": 22.76296329498291
    },
    {
      "step": 600,
      "train_loss": 0.0,
      "eval_acc": 1.0,
      "eval_loss": 0.0,
      "elapsed_s": 26.34870934486389
    },
    {
      "step": 700,
      "train_loss": 0.0,
      "eval_acc": 1.0,
      "eval_loss": 0.0,
      "elapsed_s": 30.063777685165405
    },
    {
      "step": 800,
      "train_loss": 0.0,
      "eval_acc": 1.0,
      "eval_loss": 0.0,
      "elapsed_s": 33.623549699783325
    },
    {
      "step": 900,
      "train_loss": 0.0,
      "eval_acc": 1.0,
      "eval_loss": 0.0,
      "elapsed_s": 37.195759773254395
    },
    {
      "step": 1000,
      "train_loss": 0.0,
      "eval_acc": 1.0,
      "eval_loss": 0.0,
      "elapsed_s": 40.78508186340332
    },
    {
      "step": 1100,
      "train_loss": 0.0,
      "eval_acc": 1.0,
      "eval_loss": 0.0,
      "elapsed_s": 44.35101556777954
    },
    {
      "step": 1200,
      "train_loss": 0.0,
      "eval_acc": 1.0,
      "eval_loss": 0.0,
      "elapsed_s": 47.91138958930969
    },
    {
      "step": 1300,
      "train_loss": 0.0,
      "eval_acc": 1.0,
      "eval_loss": 0.0,
      "elapsed_s": 51.47762989997864
    },
    {
      "step": 1400,
      "train_loss": 0.0,
      "eval_acc": 1.0,
      "eval_loss": 0.0,
      "elapsed_s": 55.04828429222107
    },
    {
      "step": 1500,
      "train_loss": 0.0,
      "eval_acc": 1.0,
      "eval_loss": 0.0,
      "elapsed_s": 58.610440731048584
    },
    {
      "step": 1600,
      "train_loss": 0.0,
      "eval_acc": 1.0,
      "eval_loss": 0.0,
      "elapsed_s": 62.201175689697266
    },
    {
      "step": 1700,
      "train_loss": 0.0,
      "eval_acc": 1.0,
      "eval_loss": 0.0,
      "elapsed_s": 65.76492071151733
    },
    {
      "step": 1800,
      "train_loss": 0.0,
      "eval_acc": 1.0,
      "eval_loss": 0.0,
      "elapsed_s": 69.32711505889893
    },
    {
      "step": 1900,
      "train_loss": 0.0,
      "eval_acc": 1.0,
      "eval_loss": 0.0,
      "elapsed_s": 72.92820644378662
    },
    {
      "step": 1999,
      "train_loss": 0.0,
      "eval_acc": 1.0,
      "eval_loss": 0.0,
      "elapsed_s": 76.49529194831848
    }
  ],
  "final_acc": 1.0,
  "final_loss": 0.0,
  "elapsed_total_s": 76.69478821754456,
  "length_extrap": {
    "128": {
      "acc": 1.0,
      "loss": 0.0,
      "B_eval": 32
    },
    "256": {
      "acc": 1.0,
      "loss": 0.0,
      "B_eval": 32
    },
    "512": {
      "acc": 1.0,
      "loss": 0.0,
      "B_eval": 32
    },
    "1024": {
      "acc": 1.0,
      "loss": 2.0609595794418567e-06,
      "B_eval": 16
    }
  }
}