{
  "task": "flag_hold_recall",
  "pattern": [
    "typed-gdn2",
    "typed-gdn2",
    "typed-gdn2",
    "typed-gdn2"
  ],
  "dim": 232,
  "depth": 4,
  "seq_len": 128,
  "batch_size": 32,
  "lr": 0.0006258734439691862,
  "seed": 42,
  "params": 8024104,
  "disable_autocast": true,
  "use_triton_e88": false,
  "linear_state": null,
  "state_activation": null,
  "use_gate": null,
  "decay_mode": null,
  "gdn_allow_neg_eigval": null,
  "e88_pos_eigval_clamp": null,
  "e88_raw_write": null,
  "knob_lr_mult": 1.0,
  "lam_max": 1.585,
  "beta_max": 2.747,
  "igain_max": null,
  "corner_mixture": null,
  "head_type_logits": "1.469,-1.3683,-3.2102,-1.2485,0.1177",
  "typed_alloc": {
    "type_names": [
      "gdn2_recall",
      "e97_track",
      "count",
      "latch",
      "nonlin"
    ],
    "fractions": {
      "gdn2_recall": 0.7179713777380834,
      "e97_track": 0.04206136840669718,
      "count": 0.006667398170084172,
      "latch": 0.04741457658799891,
      "nonlin": 0.1858852790971363
    },
    "counts": {
      "gdn2_recall": 35,
      "e97_track": 2,
      "count": 0,
      "latch": 2,
      "nonlin": 9
    },
    "n_gdn": 35,
    "n_unified": 13,
    "unified_counts": [
      2,
      0,
      2,
      9
    ]
  },
  "spec_reg": null,
  "spec_reg_weight": 1.0,
  "spec_reg_anneal": 0.5,
  "curriculum": null,
  "random_baseline_acc": 0.5,
  "steps": [
    {
      "step": 0,
      "train_loss": 147.8880157470703,
      "eval_acc": 0.0,
      "eval_loss": 62.6505184173584,
      "elapsed_s": 4.744773864746094
    },
    {
      "step": 100,
      "train_loss": 7.450580152834618e-09,
      "eval_acc": 1.0,
      "eval_loss": 1.313163267013806e-07,
      "elapsed_s": 9.054900407791138
    },
    {
      "step": 200,
      "train_loss": 0.0,
      "eval_acc": 1.0,
      "eval_loss": 3.725290076417309e-09,
      "elapsed_s": 12.730530261993408
    },
    {
      "step": 300,
      "train_loss": 0.0,
      "eval_acc": 1.0,
      "eval_loss": 0.0,
      "elapsed_s": 16.41309952735901
    },
    {
      "step": 400,
      "train_loss": 0.0,
      "eval_acc": 1.0,
      "eval_loss": 0.0,
      "elapsed_s": 20.074115991592407
    },
    {
      "step": 500,
      "train_loss": 0.0,
      "eval_acc": 1.0,
      "eval_loss": 0.0,
      "elapsed_s": 23.761893033981323
    },
    {
      "step": 600,
      "train_loss": 0.0,
      "eval_acc": 1.0,
      "eval_loss": 0.0,
      "elapsed_s": 27.36748719215393
    },
    {
      "step": 700,
      "train_loss": 0.0,
      "eval_acc": 1.0,
      "eval_loss": 0.0,
      "elapsed_s": 30.96432876586914
    },
    {
      "step": 800,
      "train_loss": 0.0,
      "eval_acc": 1.0,
      "eval_loss": 0.0,
      "elapsed_s": 34.57343816757202
    },
    {
      "step": 900,
      "train_loss": 0.0,
      "eval_acc": 1.0,
      "eval_loss": 0.0,
      "elapsed_s": 38.22235465049744
    },
    {
      "step": 1000,
      "train_loss": 0.0,
      "eval_acc": 1.0,
      "eval_loss": 0.0,
      "elapsed_s": 41.83632969856262
    },
    {
      "step": 1100,
      "train_loss": 0.0,
      "eval_acc": 1.0,
      "eval_loss": 0.0,
      "elapsed_s": 45.4605016708374
    },
    {
      "step": 1200,
      "train_loss": 0.0,
      "eval_acc": 1.0,
      "eval_loss": 0.0,
      "elapsed_s": 49.09380745887756
    },
    {
      "step": 1300,
      "train_loss": 0.0,
      "eval_acc": 1.0,
      "eval_loss": 0.0,
      "elapsed_s": 52.759929895401
    },
    {
      "step": 1400,
      "train_loss": 0.0,
      "eval_acc": 1.0,
      "eval_loss": 0.0,
      "elapsed_s": 56.45887327194214
    },
    {
      "step": 1500,
      "train_loss": 0.0,
      "eval_acc": 1.0,
      "eval_loss": 0.0,
      "elapsed_s": 60.13394284248352
    },
    {
      "step": 1600,
      "train_loss": 0.0,
      "eval_acc": 1.0,
      "eval_loss": 0.0,
      "elapsed_s": 63.79682803153992
    },
    {
      "step": 1700,
      "train_loss": 0.0,
      "eval_acc": 1.0,
      "eval_loss": 0.0,
      "elapsed_s": 67.46245551109314
    },
    {
      "step": 1800,
      "train_loss": 0.0,
      "eval_acc": 1.0,
      "eval_loss": 0.0,
      "elapsed_s": 71.14708232879639
    },
    {
      "step": 1900,
      "train_loss": 0.0,
      "eval_acc": 1.0,
      "eval_loss": 0.0,
      "elapsed_s": 74.83395791053772
    },
    {
      "step": 1999,
      "train_loss": 0.0,
      "eval_acc": 1.0,
      "eval_loss": 0.0,
      "elapsed_s": 78.43616676330566
    }
  ],
  "final_acc": 1.0,
  "final_loss": 0.0,
  "elapsed_total_s": 78.63921308517456,
  "length_extrap": {
    "128": {
      "acc": 1.0,
      "loss": 0.0,
      "B_eval": 32
    },
    "256": {
      "acc": 1.0,
      "loss": 0.0,
      "B_eval": 32
    },
    "512": {
      "acc": 1.0,
      "loss": 3.7252898543727042e-09,
      "B_eval": 32
    },
    "1024": {
      "acc": 0.984375,
      "loss": 0.015637452289634923,
      "B_eval": 16
    }
  }
}